sanhe_confluence_sdk/__init__.py
sanhe_confluence_sdk/_version.py
sanhe_confluence_sdk/api.py
sanhe_confluence_sdk/client.py
sanhe_confluence_sdk/methods/__init__.py
sanhe_confluence_sdk/methods/children/__init__.py
sanhe_confluence_sdk/methods/children/get_direct_page_children.py
sanhe_confluence_sdk/methods/children/get_folder_direct_children.py
sanhe_confluence_sdk/methods/common/__init__.py
sanhe_confluence_sdk/methods/common/links.py
sanhe_confluence_sdk/methods/descendant/__init__.py
sanhe_confluence_sdk/methods/descendant/get_folder_descendants.py
sanhe_confluence_sdk/methods/descendant/get_page_descendants.py
sanhe_confluence_sdk/methods/folder/__init__.py
sanhe_confluence_sdk/methods/folder/create_folder.py
sanhe_confluence_sdk/methods/folder/delete_folder.py
sanhe_confluence_sdk/methods/folder/get_folder.py
sanhe_confluence_sdk/methods/label/__init__.py
sanhe_confluence_sdk/methods/label/get_labels.py
sanhe_confluence_sdk/methods/label/get_labels_for_page.py
sanhe_confluence_sdk/methods/label/get_labels_for_space.py
sanhe_confluence_sdk/methods/m.py
sanhe_confluence_sdk/methods/model.py
sanhe_confluence_sdk/methods/page/__init__.py
sanhe_confluence_sdk/methods/page/create_page.py
sanhe_confluence_sdk/methods/page/delete_page.py
sanhe_confluence_sdk/methods/page/get_page.py
sanhe_confluence_sdk/methods/page/get_pages.py
sanhe_confluence_sdk/methods/page/get_pages_for_label.py
sanhe_confluence_sdk/methods/page/get_pages_in_space.py
sanhe_confluence_sdk/methods/page/update_page.py
sanhe_confluence_sdk/methods/page/update_page_title.py
sanhe_confluence_sdk/methods/space/__init__.py
sanhe_confluence_sdk/methods/space/create_space.py
sanhe_confluence_sdk/methods/space/get_space.py
sanhe_confluence_sdk/methods/space/get_spaces.py
sanhe_confluence_sdk/pagi.py
sanhe_confluence_sdk/paths.py
sanhe_confluence_sdk/vendor/__init__.py
sanhe_confluence_sdk/vendor/pytest_cov_helper.py
sanhe_confluence_sdk-0.1.3.dist-info/AUTHORS.rst
sanhe_confluence_sdk-0.1.3.dist-info/LICENSE.txt
sanhe_confluence_sdk-0.1.3.dist-info/METADATA
sanhe_confluence_sdk-0.1.3.dist-info/WHEEL
sanhe_confluence_sdk-0.1.3.dist-info/RECORD
